[{"line":1,"elements":[{"start_timestamp":"2022-08-31T19:21:53.355Z","line":12,"name":"Valid user login","description":"","id":"login;valid-user-login;;2","type":"scenario","keyword":"Scenario Outline","steps":[{"result":{"duration":528000000,"status":"passed"},"line":5,"name":"I am at the login page","match":{"location":"com.revmo.steps.LoginSteps.i_am_at_login_page()"},"keyword":"Given "}]},{"start_timestamp":"2022-08-31T19:21:55.491Z","line":13,"name":"Valid user login","description":"","id":"login;valid-user-login;;3","type":"scenario","keyword":"Scenario Outline","steps":[{"result":{"duration":514000000,"status":"passed"},"line":5,"name":"I am at the login page","match":{"location":"com.revmo.steps.LoginSteps.i_am_at_login_page()"},"keyword":"Given "}]},{"start_timestamp":"2022-08-31T19:21:57.571Z","line":14,"name":"Valid user login","description":"","id":"login;valid-user-login;;4","type":"scenario","keyword":"Scenario Outline","steps":[{"result":{"duration":495000000,"status":"passed"},"line":5,"name":"I am at the login page","match":{"location":"com.revmo.steps.LoginSteps.i_am_at_login_page()"},"keyword":"Given "}]}],"name":"Login","description":"","id":"login","keyword":"Feature","uri":"file:src/test/resources/login.feature","tags":[]}]